forgejs/__init__.py
forgejs/cli.py
forgejs-1.0.0.dist-info/METADATA
forgejs-1.0.0.dist-info/WHEEL
forgejs-1.0.0.dist-info/entry_points.txt
forgejs-1.0.0.dist-info/top_level.txt
forgejs-1.0.0.dist-info/RECORD
