Metadata-Version: 2.4
Name: forgejs
Version: 1.0.0
Summary: ForgeJS CLI para scaffolding de proyectos JavaScript/TypeScript
Home-page: https://github.com/BenjaMorenoo/ForgeJS-Templates
Author: DonHuea
License: MIT
Classifier: Programming Language :: Python :: 3
Classifier: License :: OSI Approved :: MIT License
Classifier: Operating System :: OS Independent
Requires-Python: >=3.7
Requires-Dist: requests
Dynamic: author
Dynamic: classifier
Dynamic: description
Dynamic: description-content-type
Dynamic: home-page
Dynamic: license
Dynamic: requires-dist
Dynamic: requires-python
Dynamic: summary
